{
  "type": "minecraft:crafting_shaped",
  "group": "lasers",
  "key": {
    "L": {
      "item": "vintageimprovements:laser_item"
    },
	"B": {
      "item": "create:brass_casing"
    },
	"S": {
      "tag": "vintageimprovements:springs/iron"
    },
	"C": {
      "item": "create:cogwheel"
    },
	"R": {
      "tag": "forge:storage_blocks/redstone"
    },
	"Q": {
      "tag": "forge:gems/quartz"
    },
	"P": {
      "item": "create:precision_mechanism"
    }
  },
  "pattern": [
    "CRC",
    "PBS",
	"QLQ"
  ],
  "result": {
    "count": 1,
    "item": "vintageimprovements:laser"
  }
}